svm2csr-0.3.1.dist-info/METADATA
svm2csr-0.3.1.dist-info/WHEEL
svm2csr/__pycache__/__init__.cpython-37.pyc
svm2csr/__pycache__/load.cpython-37.pyc
svm2csr/load.py
svm2csr/__init__.py
svm2csr/svm2csr.cpython-36m-x86_64-linux-gnu.so
svm2csr-0.3.1.dist-info/RECORD
