Metadata-Version: 2.1
Name: svm2csr
Version: 0.3.1
Classifier: License :: OSI Approved :: Apache Software License 2.0
Classifier: Programming Language :: Python
Classifier: Programming Language :: Python :: 3.6
Classifier: Programming Language :: Python :: 3.7
Classifier: Programming Language :: Python :: 3.8
Classifier: Programming Language :: Python :: 3.9
Requires-Dist: numpy>=1.16.5
Requires-Dist: scipy>=1.5
Requires-Dist: scikit-learn>=0.22
Summary: Loads SVMlight text files into scipy sparse CSR matrices in parallel.
Author: Vladimir Feinberg
Maintainer: Vladimir Feinberg
Maintainer-Email: vladimir.feinberg@gmail.com
License: Apache Software License 2.0
Requires-Python: >=3.6
Project-URL: github, https://github.com/vlad17/svm2csr
